phoenixtools/__init__.py
phoenixtools-0.0.1.dist-info/METADATA
phoenixtools-0.0.1.dist-info/WHEEL
phoenixtools-0.0.1.dist-info/top_level.txt
phoenixtools-0.0.1.dist-info/RECORD
